configure.py
configure_fork-0.6.2.dist-info/AUTHORS
configure_fork-0.6.2.dist-info/METADATA
configure_fork-0.6.2.dist-info/WHEEL
configure_fork-0.6.2.dist-info/top_level.txt
configure_fork-0.6.2.dist-info/zip-safe
configure_fork-0.6.2.dist-info/RECORD
