Metadata-Version: 2.1
Name: configure-fork
Version: 0.6.2
Summary: configuration toolkit based on YAML
Home-page: https://github.com/alfred82santa/configure
Author: Andrey Popp, Alexander Solovyov, Alfred Santacatalina
Author-email: Andrey Popp <8mayday@gmail.com>, Alexander Solovyov <alexander@solovyov.net>, Alfred Santacatalina <alfred82santa@gmail.com>
License: UNKNOWN
Platform: UNKNOWN
Classifier: Intended Audience :: Developers
Classifier: Programming Language :: Python
Classifier: Programming Language :: Python :: 3.6
Classifier: Programming Language :: Python :: 3.7
Classifier: Programming Language :: Python :: 3.8
Classifier: Programming Language :: Python :: 3.9
Classifier: Programming Language :: Python :: 3.10
Classifier: Development Status :: 4 - Beta
License-File: AUTHORS
Requires-Dist: pyyaml
